pydischarge/__init__.py
pydischarge/_version.py
pydischarge/conftest.py
pydischarge/astro/__init__.py
pydischarge/astro/range.py
pydischarge/astro/tests/__init__.py
pydischarge/astro/tests/test_range.py
pydischarge/cli/__init__.py
pydischarge/cli/cliproduct.py
pydischarge/cli/coherence.py
pydischarge/cli/coherencegram.py
pydischarge/cli/qtransform.py
pydischarge/cli/spectrogram.py
pydischarge/cli/spectrum.py
pydischarge/cli/timeseries.py
pydischarge/cli/transferfunction.py
pydischarge/cli/tests/__init__.py
pydischarge/cli/tests/base.py
pydischarge/cli/tests/test_coherence.py
pydischarge/cli/tests/test_coherencegram.py
pydischarge/cli/tests/test_pydischarge_plot.py
pydischarge/cli/tests/test_qtransform.py
pydischarge/cli/tests/test_spectrogram.py
pydischarge/cli/tests/test_spectrum.py
pydischarge/cli/tests/test_timeseries.py
pydischarge/cli/tests/test_transferfunction.py
pydischarge/detector/__init__.py
pydischarge/detector/channel.py
pydischarge/detector/units.py
pydischarge/detector/io/__init__.py
pydischarge/detector/io/cis.py
pydischarge/detector/io/clf.py
pydischarge/detector/io/omega.py
pydischarge/detector/tests/__init__.py
pydischarge/detector/tests/test_channel.py
pydischarge/detector/tests/test_units.py
pydischarge/frequencyseries/__init__.py
pydischarge/frequencyseries/_fdcommon.py
pydischarge/frequencyseries/frequencyseries.py
pydischarge/frequencyseries/hist.py
pydischarge/frequencyseries/io/__init__.py
pydischarge/frequencyseries/io/ascii.py
pydischarge/frequencyseries/io/hdf5.py
pydischarge/frequencyseries/io/ligolw.py
pydischarge/frequencyseries/tests/__init__.py
pydischarge/frequencyseries/tests/test_frequencyseries.py
pydischarge/frequencyseries/tests/test_hist.py
pydischarge/io/__init__.py
pydischarge/io/_framecpp.py
pydischarge/io/cache.py
pydischarge/io/datafind.py
pydischarge/io/ffldatafind.py
pydischarge/io/gwf.py
pydischarge/io/hdf5.py
pydischarge/io/kerberos.py
pydischarge/io/ligolw.py
pydischarge/io/mp.py
pydischarge/io/nds2.py
pydischarge-0.0.5.dist-info/LICENSE
pydischarge-0.0.5.dist-info/METADATA
pydischarge-0.0.5.dist-info/WHEEL
pydischarge-0.0.5.dist-info/entry_points.txt
pydischarge-0.0.5.dist-info/top_level.txt
pydischarge-0.0.5.dist-info/RECORD
