Metadata-Version: 2.1
Name: pydischarge
Version: 0.0.5
Summary: A python package for gravitational-wave astrophysics
Author-email: Duncan Macleod <duncan.macleod@ligo.org>
License: GPL-3.0-or-later
Project-URL: Bug Tracker, https://github.com/pydischarge/pydischarge/issues
Project-URL: Discussion Forum, https://pydischarge.slack.com
Project-URL: Documentation, https://pydischarge.github.io/docs/
Project-URL: Source Code, https://github.com/pydischarge/pydischarge
Classifier: Development Status :: 5 - Production/Stable
Classifier: Intended Audience :: Science/Research
Classifier: License :: OSI Approved :: GNU General Public License v3 or later (GPLv3+)
Classifier: Natural Language :: English
Classifier: Operating System :: OS Independent
Classifier: Programming Language :: Python
Classifier: Programming Language :: Python :: 3
Classifier: Programming Language :: Python :: 3.7
Classifier: Programming Language :: Python :: 3.8
Classifier: Programming Language :: Python :: 3.9
Classifier: Programming Language :: Python :: 3.10
Classifier: Programming Language :: Python :: 3.11
Classifier: Topic :: Scientific/Engineering :: Astronomy
Classifier: Topic :: Scientific/Engineering :: Physics
Requires-Python: >=3.7
License-File: LICENSE
Requires-Dist: astropy (>=4.3.0)
Requires-Dist: dqsegdb2
Requires-Dist: gwdatafind (>=1.1.0)
Requires-Dist: gwosc (>=0.5.3)
Requires-Dist: h5py (>=2.8.0)
Requires-Dist: ligo-segments (>=1.0.0)
Requires-Dist: ligotimegps (>=1.2.1)
Requires-Dist: matplotlib (>=3.3.0)
Requires-Dist: numpy (>=1.17)
Requires-Dist: python-dateutil
Requires-Dist: requests
Requires-Dist: scipy (>=1.2.0)
Requires-Dist: tqdm (>=4.10.0)
Provides-Extra: astro
Requires-Dist: inspiral-range ; extra == 'astro'
Provides-Extra: conda
Requires-Dist: python-framel (>=8.40.1) ; extra == 'conda'
Requires-Dist: python-nds2-client ; extra == 'conda'
Requires-Dist: python-ldas-tools-framecpp ; (sys_platform != "win32") and extra == 'conda'
Provides-Extra: dev
Requires-Dist: ciecplib ; extra == 'dev'
Requires-Dist: dateparser (>=1.1.2) ; extra == 'dev'
Requires-Dist: psycopg2 ; extra == 'dev'
Requires-Dist: pymysql ; extra == 'dev'
Requires-Dist: pyRXP ; extra == 'dev'
Requires-Dist: sqlalchemy ; extra == 'dev'
Requires-Dist: uproot (>=4.1.5) ; extra == 'dev'
Requires-Dist: maya ; (python_version < "3.11") and extra == 'dev'
Requires-Dist: lalsuite ; (sys_platform != "win32") and extra == 'dev'
Requires-Dist: lscsoft-glue ; (sys_platform != "win32") and extra == 'dev'
Requires-Dist: pycbc (>=1.13.4) ; (sys_platform != "win32") and extra == 'dev'
Requires-Dist: python-ligo-lw (>=1.7.0) ; (sys_platform != "win32") and extra == 'dev'
Provides-Extra: docs
Requires-Dist: numpydoc (>=0.8.0) ; extra == 'docs'
Requires-Dist: Sphinx (>=4.4.0) ; extra == 'docs'
Requires-Dist: sphinx-automodapi ; extra == 'docs'
Requires-Dist: sphinx-immaterial (>=0.7.3) ; extra == 'docs'
Requires-Dist: sphinx-panels (>=0.6.0) ; extra == 'docs'
Requires-Dist: sphinxcontrib-programoutput ; extra == 'docs'
Provides-Extra: test
Requires-Dist: coverage[toml] (>=5.0) ; extra == 'test'
Requires-Dist: pytest (>=3.9.1) ; extra == 'test'
Requires-Dist: pytest-freezegun ; extra == 'test'
Requires-Dist: pytest-cov (>=2.4.0) ; extra == 'test'
Requires-Dist: pytest-requires ; extra == 'test'
Requires-Dist: pytest-socket ; extra == 'test'
Requires-Dist: pytest-xdist ; extra == 'test'
Requires-Dist: requests-mock ; extra == 'test'
